[
  {
    "date": "2025-05-01",
    "bpMarketCap": 73316482080,
    "coinMarketCap": 51369344400
  },
  {
    "date": "2025-05-02",
    "bpMarketCap": 73947613920,
    "coinMarketCap": 52295676840
  },
  {
    "date": "2025-05-03",
    "bpMarketCap": 73947613920,
    "coinMarketCap": 52295676840
  },
  {
    "date": "2025-05-04",
    "bpMarketCap": 73947613920,
    "coinMarketCap": 52295676840
  },
  {
    "date": "2025-05-05",
    "bpMarketCap": 76735112880,
    "coinMarketCap": 50884487200
  },
  {
    "date": "2025-05-06",
    "bpMarketCap": 74683934400,
    "coinMarketCap": 50243965320
  },
  {
    "date": "2025-05-07",
    "bpMarketCap": 73973911080,
    "coinMarketCap": 50159753280
  },
  {
    "date": "2025-05-08",
    "bpMarketCap": 75183580440,
    "coinMarketCap": 52696322000
  },
  {
    "date": "2025-05-09",
    "bpMarketCap": 78286645320,
    "coinMarketCap": 50864072160
  },
  {
    "date": "2025-05-10",
    "bpMarketCap": 78286645320,
    "coinMarketCap": 50864072160
  },
  {
    "date": "2025-05-11",
    "bpMarketCap": 78286645320,
    "coinMarketCap": 50864072160
  },
  {
    "date": "2025-05-12",
    "bpMarketCap": 79391126040,
    "coinMarketCap": 52880057360
  },
  {
    "date": "2025-05-13",
    "bpMarketCap": 80364120960,
    "coinMarketCap": 65557797199
  },
  {
    "date": "2025-05-14",
    "bpMarketCap": 79838177760,
    "coinMarketCap": 67219071080
  },
  {
    "date": "2025-05-15",
    "bpMarketCap": 79180748760,
    "coinMarketCap": 62378154720
  },
  {
    "date": "2025-05-16",
    "bpMarketCap": 78260348160,
    "coinMarketCap": 67997394479
  },
  {
    "date": "2025-05-17",
    "bpMarketCap": 78260348160,
    "coinMarketCap": 67997394479
  },
  {
    "date": "2025-05-18",
    "bpMarketCap": 78260348160,
    "coinMarketCap": 67997394479
  },
  {
    "date": "2025-05-19",
    "bpMarketCap": 77313650400,
    "coinMarketCap": 67367080120
  },
  {
    "date": "2025-05-20",
    "bpMarketCap": 76787707200,
    "coinMarketCap": 66701039440
  },
  {
    "date": "2025-05-21",
    "bpMarketCap": 75946198080,
    "coinMarketCap": 66091140120
  },
  {
    "date": "2025-05-22",
    "bpMarketCap": 76103981040,
    "coinMarketCap": 69398376600
  },
  {
    "date": "2025-05-23",
    "bpMarketCap": 76498438440,
    "coinMarketCap": 67155274080
  },
  {
    "date": "2025-05-24",
    "bpMarketCap": 76498438440,
    "coinMarketCap": 67155274080
  },
  {
    "date": "2025-05-25",
    "bpMarketCap": 76498438440,
    "coinMarketCap": 67155274080
  },
  {
    "date": "2025-05-26",
    "bpMarketCap": 76498438440,
    "coinMarketCap": 67155274080
  },
  {
    "date": "2025-05-27",
    "bpMarketCap": 76656221400,
    "coinMarketCap": 67982083199
  },
  {
    "date": "2025-05-28",
    "bpMarketCap": 76103981040,
    "coinMarketCap": 64891756520
  },
  {
    "date": "2025-05-29",
    "bpMarketCap": 76708815720,
    "coinMarketCap": 63500981920
  },
  {
    "date": "2025-05-30",
    "bpMarketCap": 76524735600,
    "coinMarketCap": 62934464560
  },
  {
    "date": "2025-05-31",
    "bpMarketCap": 76524735600,
    "coinMarketCap": 62934464560
  },
  {
    "date": "2025-06-01",
    "bpMarketCap": 76524735600,
    "coinMarketCap": 62934464560
  },
  {
    "date": "2025-06-02",
    "bpMarketCap": 77786999280,
    "coinMarketCap": 62959983360
  },
  {
    "date": "2025-06-03",
    "bpMarketCap": 77734404960,
    "coinMarketCap": 66070725080
  },
  {
    "date": "2025-06-04",
    "bpMarketCap": 76051386720,
    "coinMarketCap": 65328128000
  },
  {
    "date": "2025-06-05",
    "bpMarketCap": 76393249800,
    "coinMarketCap": 62316909600
  },
  {
    "date": "2025-06-06",
    "bpMarketCap": 77024381640,
    "coinMarketCap": 64121088760
  },
  {
    "date": "2025-06-07",
    "bpMarketCap": 77024381640,
    "coinMarketCap": 64121088760
  },
  {
    "date": "2025-06-08",
    "bpMarketCap": 77024381640,
    "coinMarketCap": 64121088760
  },
  {
    "date": "2025-06-09",
    "bpMarketCap": 77471433360,
    "coinMarketCap": 65488896440
  },
  {
    "date": "2025-06-10",
    "bpMarketCap": 79496314680,
    "coinMarketCap": 65057628720
  },
  {
    "date": "2025-06-11",
    "bpMarketCap": 81021549960,
    "coinMarketCap": 63970527840
  },
  {
    "date": "2025-06-12",
    "bpMarketCap": 81310818720,
    "coinMarketCap": 61513067400
  },
  {
    "date": "2025-06-13",
    "bpMarketCap": 83414591520,
    "coinMarketCap": 61936679480
  },
  {
    "date": "2025-06-14",
    "bpMarketCap": 83414591520,
    "coinMarketCap": 61936679480
  },
  {
    "date": "2025-06-15",
    "bpMarketCap": 83414591520,
    "coinMarketCap": 61936679480
  },
  {
    "date": "2025-06-16",
    "bpMarketCap": 81941950560,
    "coinMarketCap": 66749525160
  },
  {
    "date": "2025-06-17",
    "bpMarketCap": 83046431280,
    "coinMarketCap": 64779473800
  },
  {
    "date": "2025-06-18",
    "bpMarketCap": 81889356240,
    "coinMarketCap": 75354464520
  },
  {
    "date": "2025-06-19",
    "bpMarketCap": 81889356240,
    "coinMarketCap": 75354464520
  },
  {
    "date": "2025-06-20",
    "bpMarketCap": 82178625000,
    "coinMarketCap": 78694875440
  },
  {
    "date": "2025-06-21",
    "bpMarketCap": 82178625000,
    "coinMarketCap": 78694875440
  },
  {
    "date": "2025-06-22",
    "bpMarketCap": 82178625000,
    "coinMarketCap": 78694875440
  },
  {
    "date": "2025-06-23",
    "bpMarketCap": 79732989120,
    "coinMarketCap": 78493276920
  },
  {
    "date": "2025-06-24",
    "bpMarketCap": 78444428280,
    "coinMarketCap": 87993926160
  },
  {
    "date": "2025-06-25",
    "bpMarketCap": 79732989120,
    "coinMarketCap": 90686159560
  },
  {
    "date": "2025-06-26",
    "bpMarketCap": 79654097640,
    "coinMarketCap": 95713363160
  },
  {
    "date": "2025-06-27",
    "bpMarketCap": 79785583440,
    "coinMarketCap": 90191094840
  },
  {
    "date": "2025-06-28",
    "bpMarketCap": 79785583440,
    "coinMarketCap": 90191094840
  },
  {
    "date": "2025-06-29",
    "bpMarketCap": 79785583440,
    "coinMarketCap": 90191094840
  },
  {
    "date": "2025-06-30",
    "bpMarketCap": 78707399880,
    "coinMarketCap": 89440842120
  },
  {
    "date": "2025-07-01",
    "bpMarketCap": 80206338000,
    "coinMarketCap": 85572192040
  },
  {
    "date": "2025-07-02",
    "bpMarketCap": 82310110800,
    "coinMarketCap": 90451386600
  },
  {
    "date": "2025-07-03",
    "bpMarketCap": 81337115880,
    "coinMarketCap": 90795890400
  },
  {
    "date": "2025-07-04",
    "bpMarketCap": 81337115880,
    "coinMarketCap": 90795890400
  },
  {
    "date": "2025-07-05",
    "bpMarketCap": 81337115880,
    "coinMarketCap": 90795890400
  },
  {
    "date": "2025-07-06",
    "bpMarketCap": 81337115880,
    "coinMarketCap": 90795890400
  },
  {
    "date": "2025-07-07",
    "bpMarketCap": 79548909000,
    "coinMarketCap": 91127634800
  },
  {
    "date": "2025-07-08",
    "bpMarketCap": 82231219320,
    "coinMarketCap": 90545806160
  },
  {
    "date": "2025-07-09",
    "bpMarketCap": 82231219320,
    "coinMarketCap": 95402033800
  },
  {
    "date": "2025-07-10",
    "bpMarketCap": 82888648320,
    "coinMarketCap": 99257924480
  },
  {
    "date": "2025-07-11",
    "bpMarketCap": 85833930240,
    "coinMarketCap": 98773067280
  },
  {
    "date": "2025-07-12",
    "bpMarketCap": 85833930240,
    "coinMarketCap": 98773067280
  },
  {
    "date": "2025-07-13",
    "bpMarketCap": 85833930240,
    "coinMarketCap": 98773067280
  },
  {
    "date": "2025-07-14",
    "bpMarketCap": 84413883600,
    "coinMarketCap": 100546623880
  },
  {
    "date": "2025-07-15",
    "bpMarketCap": 83782751760,
    "coinMarketCap": 99018047760
  },
  {
    "date": "2025-07-16",
    "bpMarketCap": 83940534720,
    "coinMarketCap": 101615861600
  },
  {
    "date": "2025-07-17",
    "bpMarketCap": 84387586440,
    "coinMarketCap": 104818471000
  },
  {
    "date": "2025-07-18",
    "bpMarketCap": 84124614840,
    "coinMarketCap": 107122818640
  },
  {
    "date": "2025-07-19",
    "bpMarketCap": 84124614840,
    "coinMarketCap": 107122818640
  },
  {
    "date": "2025-07-20",
    "bpMarketCap": 84124614840,
    "coinMarketCap": 107122818640
  },
  {
    "date": "2025-07-21",
    "bpMarketCap": 84755746679,
    "coinMarketCap": 105553412440
  },
  {
    "date": "2025-07-22",
    "bpMarketCap": 85518364320,
    "coinMarketCap": 103208234720
  },
  {
    "date": "2025-07-23",
    "bpMarketCap": 86018010360,
    "coinMarketCap": 101516338280
  },
  {
    "date": "2025-07-24",
    "bpMarketCap": 84492775080,
    "coinMarketCap": 101233079600
  },
  {
    "date": "2025-07-25",
    "bpMarketCap": 84676855200,
    "coinMarketCap": 99946932080
  },
  {
    "date": "2025-07-26",
    "bpMarketCap": 84676855200,
    "coinMarketCap": 99946932080
  },
  {
    "date": "2025-07-27",
    "bpMarketCap": 84676855200,
    "coinMarketCap": 99946932080
  },
  {
    "date": "2025-07-28",
    "bpMarketCap": 85912821720,
    "coinMarketCap": 96841294120
  },
  {
    "date": "2025-07-29",
    "bpMarketCap": 86675439360,
    "coinMarketCap": 94787030720
  },
  {
    "date": "2025-07-30",
    "bpMarketCap": 84808341000,
    "coinMarketCap": 96328366240
  },
  {
    "date": "2025-07-31",
    "bpMarketCap": 84545369400,
    "coinMarketCap": 96399818880
  },
  {
    "date": "2025-08-01",
    "bpMarketCap": 83493483000,
    "coinMarketCap": 80305111720
  },
  {
    "date": "2025-08-02",
    "bpMarketCap": 83493483000,
    "coinMarketCap": 80305111720
  },
  {
    "date": "2025-08-03",
    "bpMarketCap": 83493483000,
    "coinMarketCap": 80305111720
  },
  {
    "date": "2025-08-04",
    "bpMarketCap": 84720729060,
    "coinMarketCap": 81193165960
  },
  {
    "date": "2025-08-05",
    "bpMarketCap": 87615158400,
    "coinMarketCap": 76043472120
  },
  {
    "date": "2025-08-06",
    "bpMarketCap": 88345284720,
    "coinMarketCap": 77469973040
  },
  {
    "date": "2025-08-07",
    "bpMarketCap": 89153638860,
    "coinMarketCap": 79309878520
  },
  {
    "date": "2025-08-08",
    "bpMarketCap": 89023259160,
    "coinMarketCap": 79246081520
  },
  {
    "date": "2025-08-09",
    "bpMarketCap": 89023259160,
    "coinMarketCap": 79246081520
  },
  {
    "date": "2025-08-10",
    "bpMarketCap": 88078812449,
    "coinMarketCap": 79789528716
  },
  {
    "date": "2025-08-11",
    "bpMarketCap": 88078812449,
    "coinMarketCap": 79789528716
  },
  {
    "date": "2025-08-12",
    "bpMarketCap": 87588629271,
    "coinMarketCap": 82122522305
  },
  {
    "date": "2025-08-13",
    "bpMarketCap": 88418123053,
    "coinMarketCap": 82893336305
  },
  {
    "date": "2025-08-14",
    "bpMarketCap": 88721548547,
    "coinMarketCap": 84021297889
  },
  {
    "date": "2025-08-15",
    "bpMarketCap": 89348682980,
    "coinMarketCap": 83476590584
  },
  {
    "date": "2025-08-16",
    "bpMarketCap": 88536048667,
    "coinMarketCap": 81590658764
  },
  {
    "date": "2025-08-17",
    "bpMarketCap": 88536048667,
    "coinMarketCap": 81590658764
  },
  {
    "date": "2025-08-18",
    "bpMarketCap": 88536048667,
    "coinMarketCap": 81590658764
  },
  {
    "date": "2025-08-19",
    "bpMarketCap": 87813930346,
    "coinMarketCap": 82407727563
  },
  {
    "date": "2025-08-20",
    "bpMarketCap": 87617136633,
    "coinMarketCap": 77613263542
  },
  {
    "date": "2025-08-21",
    "bpMarketCap": 88118498031,
    "coinMarketCap": 78209361584
  },
  {
    "date": "2025-08-22",
    "bpMarketCap": 88308669753,
    "coinMarketCap": 77153342326
  },
  {
    "date": "2025-08-23",
    "bpMarketCap": 89560075618,
    "coinMarketCap": 82181620868
  },
  {
    "date": "2025-08-24",
    "bpMarketCap": 89560075618,
    "coinMarketCap": 82181620868
  },
  {
    "date": "2025-08-25",
    "bpMarketCap": 89560075618,
    "coinMarketCap": 82181620868
  },
  {
    "date": "2025-08-26",
    "bpMarketCap": 90153016764,
    "coinMarketCap": 78623028000
  },
  {
    "date": "2025-08-27",
    "bpMarketCap": 89373011352,
    "coinMarketCap": 79260237063
  },
  {
    "date": "2025-08-28",
    "bpMarketCap": 89933507452,
    "coinMarketCap": 79386134174
  },
  {
    "date": "2025-08-29",
    "bpMarketCap": 91119214870,
    "coinMarketCap": 79257665174
  },
  {
    "date": "2025-08-30",
    "bpMarketCap": 90803210020,
    "coinMarketCap": 78247900716
  },
  {
    "date": "2025-08-31",
    "bpMarketCap": 90803210020,
    "coinMarketCap": 78247900716
  },
  {
    "date": "2025-09-01",
    "bpMarketCap": 90803210020,
    "coinMarketCap": 78247900716
  },
  {
    "date": "2025-09-02",
    "bpMarketCap": 90803210020,
    "coinMarketCap": 78247900716
  },
  {
    "date": "2025-09-03",
    "bpMarketCap": 90796166275,
    "coinMarketCap": 77996098653
  },
  {
    "date": "2025-09-04",
    "bpMarketCap": 90912371790,
    "coinMarketCap": 77674926153
  },
  {
    "date": "2025-09-05",
    "bpMarketCap": 90912151271,
    "coinMarketCap": 78828575264
  },
  {
    "date": "2025-09-06",
    "bpMarketCap": 89931469066,
    "coinMarketCap": 78828575853
  },
  {
    "date": "2025-09-07",
    "bpMarketCap": 88667913683,
    "coinMarketCap": 76842449542
  },
  {
    "date": "2025-09-08",
    "bpMarketCap": 88667913683,
    "coinMarketCap": 76842449542
  },
  {
    "date": "2025-09-09",
    "bpMarketCap": 87333851462,
    "coinMarketCap": 77646666736
  },
  {
    "date": "2025-09-10",
    "bpMarketCap": 87797435066,
    "coinMarketCap": 81906695326
  },
  {
    "date": "2025-09-11",
    "bpMarketCap": 89510815385,
    "coinMarketCap": 81022827979
  },
  {
    "date": "2025-09-12",
    "bpMarketCap": 88758181634,
    "coinMarketCap": 83235068236
  },
  {
    "date": "2025-09-13",
    "bpMarketCap": 88845345684,
    "coinMarketCap": 83001253716
  },
  {
    "date": "2025-09-14",
    "bpMarketCap": 88845345684,
    "coinMarketCap": 83001253716
  },
  {
    "date": "2025-09-15",
    "bpMarketCap": 88845345684,
    "coinMarketCap": 83001253716
  },
  {
    "date": "2025-09-16",
    "bpMarketCap": 88845423506,
    "coinMarketCap": 83001273048
  },
  {
    "date": "2025-09-17",
    "bpMarketCap": 88759848881,
    "coinMarketCap": 84252540521
  },
  {
    "date": "2025-09-18",
    "bpMarketCap": 88308319891,
    "coinMarketCap": 82364094981
  },
  {
    "date": "2025-09-19",
    "bpMarketCap": 88965621917,
    "coinMarketCap": 88163191066
  },
  {
    "date": "2025-09-20",
    "bpMarketCap": 88361656691,
    "coinMarketCap": 87991039051
  },
  {
    "date": "2025-09-21",
    "bpMarketCap": 89578955824,
    "coinMarketCap": 87991039051
  },
  {
    "date": "2025-09-22",
    "bpMarketCap": 89578955824,
    "coinMarketCap": 87991039051
  },
  {
    "date": "2025-09-23",
    "bpMarketCap": 89578955848,
    "coinMarketCap": 85290624353
  },
  {
    "date": "2025-09-24",
    "bpMarketCap": 90543298610,
    "coinMarketCap": 82238197793
  },
  {
    "date": "2025-09-25",
    "bpMarketCap": 90614222844,
    "coinMarketCap": 82674987955
  },
  {
    "date": "2025-09-26",
    "bpMarketCap": 90737314891,
    "coinMarketCap": 82674991335
  },
  {
    "date": "2025-09-27",
    "bpMarketCap": 92632519208,
    "coinMarketCap": 84265463604
  },
  {
    "date": "2025-09-28",
    "bpMarketCap": 91832566505,
    "coinMarketCap": 80316297556
  },
  {
    "date": "2025-09-29",
    "bpMarketCap": 91832566505,
    "coinMarketCap": 80316297556
  },
  {
    "date": "2025-09-30",
    "bpMarketCap": 89413892094,
    "coinMarketCap": 85814772547
  },
  {
    "date": "2025-10-01",
    "bpMarketCap": 91409485224,
    "coinMarketCap": 81157959063
  },
  {
    "date": "2025-10-02",
    "bpMarketCap": 91409485224,
    "coinMarketCap": 80316301611
  },
  {
    "date": "2025-10-03",
    "bpMarketCap": 89817913747,
    "coinMarketCap": 86325463702
  },
  {
    "date": "2025-10-04",
    "bpMarketCap": 89519244005,
    "coinMarketCap": 97641635600
  },
  {
    "date": "2025-10-05",
    "bpMarketCap": 88650415255,
    "coinMarketCap": 97641635600
  },
  {
    "date": "2025-10-06",
    "bpMarketCap": 88650415255,
    "coinMarketCap": 97641635600
  },
  {
    "date": "2025-10-07",
    "bpMarketCap": 89595356800,
    "coinMarketCap": 97120938132
  },
  {
    "date": "2025-10-08",
    "bpMarketCap": 89903993706,
    "coinMarketCap": 96552220324
  },
  {
    "date": "2025-10-09",
    "bpMarketCap": 88726954976,
    "coinMarketCap": 99504437239
  },
  {
    "date": "2025-10-10",
    "bpMarketCap": 89414894595,
    "coinMarketCap": 99435066759
  },
  {
    "date": "2025-10-11",
    "bpMarketCap": 89336013754,
    "coinMarketCap": 91729493940
  },
  {
    "date": "2025-10-12",
    "bpMarketCap": 89336013754,
    "coinMarketCap": 91729493940
  },
  {
    "date": "2025-10-13",
    "bpMarketCap": 89336013754,
    "coinMarketCap": 91729493940
  },
  {
    "date": "2025-10-14",
    "bpMarketCap": 86537020916,
    "coinMarketCap": 91724350158
  },
  {
    "date": "2025-10-15",
    "bpMarketCap": 86192176717,
    "coinMarketCap": 91724349354
  },
  {
    "date": "2025-10-16",
    "bpMarketCap": 86790913075,
    "coinMarketCap": 90314444944
  }
]